src/AstPrinter.py
src/Clock.py
src/Environment.py
src/Expr.py
src/GenerateAst.py
src/Interpreter.py
src/Jesse.py
src/JesseCallable.py
src/JesseFunction.py
src/JesseRuntimeError.py
src/Parser.py
src/Resolver.py
src/ReturnException.py
src/Scanner.py
src/Stmt.py
src/Token.py
src/TokenType.py
jesse_lang-0.0.1.dist-info/METADATA
jesse_lang-0.0.1.dist-info/WHEEL
jesse_lang-0.0.1.dist-info/RECORD
