Metadata-Version: 2.1
Name: jesse_lang
Version: 0.0.1
Summary: The jesse programming language
Project-URL: Homepage, https://github.com/AkshayWarrier/jesse
Project-URL: Bug Tracker, https://github.com/AkshayWarrier/jesse/issues
Author-email: Akshay Warrier <aksmen121@gmail.com>
Classifier: License :: OSI Approved :: MIT License
Classifier: Operating System :: OS Independent
Classifier: Programming Language :: Python :: 3
Requires-Python: >=3.7
